cv_ws_streamer/core.py
cv_ws_streamer-0.1.0.dist-info/METADATA
cv_ws_streamer-0.1.0.dist-info/WHEEL
cv_ws_streamer-0.1.0.dist-info/top_level.txt
cv_ws_streamer-0.1.0.dist-info/RECORD
