Metadata-Version: 2.4
Name: cv-ws-streamer
Version: 0.1.0
Summary: High-performance bridge connecting Python OpenCV to React using Binary WebSockets
Project-URL: Homepage, https://github.com/example/cv-ws-streamer
Classifier: Programming Language :: Python :: 3
Classifier: License :: OSI Approved :: MIT License
Classifier: Operating System :: OS Independent
Requires-Python: >=3.8
Requires-Dist: fastapi
Requires-Dist: uvicorn[standard]
Requires-Dist: opencv-python
Requires-Dist: numpy
Requires-Dist: websockets
